Metadata-Version: 2.1
Name: pykofamsearch
Version: 2024.11.8.post1
Summary: Fast implementation of KofamScan optimized for high-memory systems using PyHmmer
Home-page: https://github.com/jolespin/pykofamsearch
Author: Josh L. Espinoza
Author-email: jolespin@newatlantis.io, jol.espinoz@gmail.com
License: MIT License
License-File: LICENSE
Requires-Dist: pyhmmer>=0.10.12
Requires-Dist: pandas
Requires-Dist: tqdm
